opendatablend/__init__.py
opendatablend/opendatablend.py
opendatablend-1.4.2.dist-info/LICENSE
opendatablend-1.4.2.dist-info/METADATA
opendatablend-1.4.2.dist-info/WHEEL
opendatablend-1.4.2.dist-info/top_level.txt
opendatablend-1.4.2.dist-info/RECORD
