Metadata-Version: 2.1
Name: opendatablend
Version: 1.4.2
Summary: The fastest way to get data from the Open Data Blend Dataset API
Home-page: https://github.com/opendatablend/opendatablend-py
Author: Open Data Blend
Author-email: info@opendatablend.io
Project-URL: Bug Tracker, https://github.com/opendatablend/opendatablend-py/issues
Classifier: Programming Language :: Python :: 3
Classifier: License :: OSI Approved :: MIT License
Classifier: Operating System :: OS Independent
Requires-Python: >=3.7
License-File: LICENSE
Requires-Dist: azure-storage-blob >=12.10.0
Requires-Dist: boto3
Requires-Dist: botocore
Requires-Dist: google-cloud-storage >=2.3.0
Requires-Dist: frictionless <5.0.0,>=4.0.0
Requires-Dist: requests
